aocov/__init__.py
aocov/covariance.py
aocov-0.1.2.dist-info/LICENSE
aocov-0.1.2.dist-info/METADATA
aocov-0.1.2.dist-info/WHEEL
aocov-0.1.2.dist-info/top_level.txt
aocov-0.1.2.dist-info/RECORD
