Metadata-Version: 2.1
Name: aocov
Version: 0.1.2
Summary: Efficient covariance computations for Adaptive Optics in Python
Home-page: https://github.com/jcranney/aocov.git
Author: Jesse Cranney
Author-email: jesse.cranney@anu.edu.au
Classifier: Programming Language :: Python :: 3
Classifier: License :: OSI Approved :: GNU General Public License (GPL)
Classifier: Operating System :: OS Independent
Requires-Python: >=3.8
License-File: LICENSE
Requires-Dist: numpy
Requires-Dist: scipy
Requires-Dist: aotools
Requires-Dist: torch
Requires-Dist: pydantic
